{
  "id": "dec-decision-table-hit-policy-21",
  "topic": "decisions-business-rules",
  "subtopic": "hit policy",
  "difficulty": "medium",
  "style": "recall",
  "kind": "single",
  "camundaVersion": "8.8",
  "question": "How does the hit policy `RULE ORDER` shape the result of a DMN decision table when several rules match the same input?",
  "options": [
    {
      "id": "a",
      "text": "It returns the outputs of all satisfied rules as a list, ordered by their row position in the table"
    },
    {
      "id": "b",
      "text": "It returns the outputs of all satisfied rules as a list, sorted alphabetically by output value"
    },
    {
      "id": "c",
      "text": "It returns the output of the first satisfied rule only, stopping evaluation after the first match"
    },
    {
      "id": "d",
      "text": "It returns the outputs of all rules in the table, using `null` for rules that were not satisfied"
    }
  ],
  "correctOptionId": "a",
  "optionExplanations": {
    "a": {
      "text": "`RULE ORDER` returns the outputs of all satisfied rules in the order in which the rules appear in the decision table."
    },
    "b": {
      "text": "The order is the row order of the rules in the table, not an alphabetical sort of output values."
    },
    "c": {
      "text": "Stopping after the first match is the behavior of `FIRST`, not `RULE ORDER`."
    },
    "d": {
      "text": "Unsatisfied rules contribute no output — `RULE ORDER` does not pad the result with `null` for non-matching rules."
    }
  },
  "explanation": "`RULE ORDER` permits multiple matching rules and includes the output of each satisfied rule in the result, ordered by the rule's position in the table. Row order in the editor therefore determines the order of the items in the resulting list.",
  "docs": [
    {
      "title": "DMN decision table hit policy",
      "url": "https://docs.camunda.io/docs/components/modeler/dmn/decision-table-hit-policy/"
    }
  ]
}
