{
  "id": "ext-properties-reference-43",
  "topic": "extensions-integrations",
  "subtopic": "spring-boot-starter",
  "difficulty": "easy",
  "style": "recall",
  "kind": "single",
  "camundaVersion": "8.8",
  "question": "What is the default value of `camunda.client.auth.connect-timeout` in the Camunda Spring Boot starter?",
  "options": [
    {
      "id": "a",
      "text": "`PT5S`"
    },
    {
      "id": "b",
      "text": "`PT10S`"
    },
    {
      "id": "c",
      "text": "`PT1S`"
    },
    {
      "id": "d",
      "text": "`null` — no timeout is applied by default."
    }
  ],
  "correctOptionId": "a",
  "optionExplanations": {
    "a": {
      "text": "The properties reference lists `camunda.client.auth.connect-timeout` (\"connection timeout for requests to the OAuth credentials provider\") with a default of `PT5S`."
    },
    "b": {
      "text": "`PT10S` is the default for `camunda.client.request-timeout`, not the OAuth connect timeout."
    },
    "c": {
      "text": "`PT1S` is the default for `camunda.client.request-timeout-offset`, not the auth connect timeout."
    },
    "d": {
      "text": "The auth connect timeout has a concrete default of `PT5S`; it is not unset."
    }
  },
  "explanation": "Both `camunda.client.auth.connect-timeout` and `camunda.client.auth.read-timeout` default to `PT5S` for requests to the OAuth credentials provider. Don't confuse these with `request-timeout` (`PT10S`) or the timeout offset (`PT1S`).",
  "docs": [
    {
      "title": "Camunda Spring Boot starter properties reference",
      "url": "https://docs.camunda.io/docs/apis-tools/camunda-spring-boot-starter/properties-reference/"
    }
  ]
}
